{
  "generatedAt": "2026-05-28T20:51:26.314Z",
  "events": [
    {
      "kind": "layout",
      "name": "MarketingGroupLayout",
      "path": "src/app/(marketing)/layout.tsx",
      "route": "/",
      "phase": "layout",
      "meta": {
        "moduleType": "layout",
        "segmentGroups": [
          "marketing"
        ]
      },
      "id": "layout:1",
      "startTimeMs": 15175.23052,
      "memoryStartMB": 370.29,
      "endTimeMs": 15285.97494,
      "durationMs": 110.7444200000009,
      "memoryEndMB": 376.66
    },
    {
      "kind": "layout",
      "name": "MarketingDefaultLocaleLayout",
      "path": "src/app/(marketing)/(default)/layout.tsx",
      "route": "/",
      "phase": "layout",
      "meta": {
        "moduleType": "layout",
        "segmentGroups": [
          "marketing",
          "default"
        ]
      },
      "id": "layout:2",
      "startTimeMs": 15190.293003,
      "memoryStartMB": 370.29,
      "endTimeMs": 16026.773961,
      "durationMs": 836.4809580000001,
      "memoryEndMB": 391.13
    },
    {
      "kind": "layout",
      "name": "MarketingGroupLayout",
      "path": "src/app/(marketing)/layout.tsx",
      "route": "/",
      "phase": "layout",
      "meta": {
        "moduleType": "layout",
        "segmentGroups": [
          "marketing"
        ]
      },
      "id": "layout:3",
      "startTimeMs": 15518.258554,
      "memoryStartMB": 381,
      "endTimeMs": 15523.843003,
      "durationMs": 5.58444899999995,
      "memoryEndMB": 381
    },
    {
      "kind": "layout",
      "name": "MarketingDefaultLocaleLayout",
      "path": "src/app/(marketing)/(default)/layout.tsx",
      "route": "/",
      "phase": "layout",
      "meta": {
        "moduleType": "layout",
        "segmentGroups": [
          "marketing",
          "default"
        ]
      },
      "id": "layout:4",
      "startTimeMs": 15520.011593,
      "memoryStartMB": 381,
      "endTimeMs": 16027.817509,
      "durationMs": 507.80591600000116,
      "memoryEndMB": 391.13
    },
    {
      "kind": "layout",
      "name": "MarketingGroupLayout",
      "path": "src/app/(marketing)/layout.tsx",
      "route": "/",
      "phase": "layout",
      "meta": {
        "moduleType": "layout",
        "segmentGroups": [
          "marketing"
        ]
      },
      "id": "layout:5",
      "startTimeMs": 15595.615792,
      "memoryStartMB": 382.13,
      "endTimeMs": 15602.164885,
      "durationMs": 6.54909299999963,
      "memoryEndMB": 382.13
    },
    {
      "kind": "layout",
      "name": "MarketingDefaultLocaleLayout",
      "path": "src/app/(marketing)/(default)/layout.tsx",
      "route": "/",
      "phase": "layout",
      "meta": {
        "moduleType": "layout",
        "segmentGroups": [
          "marketing",
          "default"
        ]
      },
      "id": "layout:6",
      "startTimeMs": 15599.673067,
      "memoryStartMB": 382.13,
      "endTimeMs": 16029.085363,
      "durationMs": 429.4122960000004,
      "memoryEndMB": 391.13
    },
    {
      "kind": "layout",
      "name": "MarketingGroupLayout",
      "path": "src/app/(marketing)/layout.tsx",
      "route": "/",
      "phase": "layout",
      "meta": {
        "moduleType": "layout",
        "segmentGroups": [
          "marketing"
        ]
      },
      "id": "layout:7",
      "startTimeMs": 15614.823461,
      "memoryStartMB": 382.25,
      "endTimeMs": 15625.387847,
      "durationMs": 10.564386000000013,
      "memoryEndMB": 382.25
    },
    {
      "kind": "layout",
      "name": "MarketingDefaultLocaleLayout",
      "path": "src/app/(marketing)/(default)/layout.tsx",
      "route": "/",
      "phase": "layout",
      "meta": {
        "moduleType": "layout",
        "segmentGroups": [
          "marketing",
          "default"
        ]
      },
      "id": "layout:8",
      "startTimeMs": 15619.583276,
      "memoryStartMB": 382.25,
      "endTimeMs": 16029.394223,
      "durationMs": 409.81094699999994,
      "memoryEndMB": 391.13
    },
    {
      "kind": "layout",
      "name": "MarketingGroupLayout",
      "path": "src/app/(marketing)/layout.tsx",
      "route": "/",
      "phase": "layout",
      "meta": {
        "moduleType": "layout",
        "segmentGroups": [
          "marketing"
        ]
      },
      "id": "layout:9",
      "startTimeMs": 15639.4421,
      "memoryStartMB": 382.38,
      "endTimeMs": 15643.139305,
      "durationMs": 3.6972050000003946,
      "memoryEndMB": 382.38
    },
    {
      "kind": "layout",
      "name": "MarketingDefaultLocaleLayout",
      "path": "src/app/(marketing)/(default)/layout.tsx",
      "route": "/",
      "phase": "layout",
      "meta": {
        "moduleType": "layout",
        "segmentGroups": [
          "marketing",
          "default"
        ]
      },
      "id": "layout:10",
      "startTimeMs": 15640.960493,
      "memoryStartMB": 382.38,
      "endTimeMs": 16029.551061,
      "durationMs": 388.5905679999996,
      "memoryEndMB": 391.13
    },
    {
      "kind": "layout",
      "name": "MarketingGroupLayout",
      "path": "src/app/(marketing)/layout.tsx",
      "route": "/",
      "phase": "layout",
      "meta": {
        "moduleType": "layout",
        "segmentGroups": [
          "marketing"
        ]
      },
      "id": "layout:11",
      "startTimeMs": 15652.506043,
      "memoryStartMB": 382.38,
      "endTimeMs": 15655.835729,
      "durationMs": 3.3296860000009474,
      "memoryEndMB": 382.38
    },
    {
      "kind": "layout",
      "name": "MarketingDefaultLocaleLayout",
      "path": "src/app/(marketing)/(default)/layout.tsx",
      "route": "/",
      "phase": "layout",
      "meta": {
        "moduleType": "layout",
        "segmentGroups": [
          "marketing",
          "default"
        ]
      },
      "id": "layout:12",
      "startTimeMs": 15653.868845,
      "memoryStartMB": 382.38,
      "endTimeMs": 16029.697313,
      "durationMs": 375.8284679999997,
      "memoryEndMB": 391.13
    },
    {
      "kind": "layout",
      "name": "MarketingGroupLayout",
      "path": "src/app/(marketing)/layout.tsx",
      "route": "/",
      "phase": "layout",
      "meta": {
        "moduleType": "layout",
        "segmentGroups": [
          "marketing"
        ]
      },
      "id": "layout:13",
      "startTimeMs": 15666.209983,
      "memoryStartMB": 382.5,
      "endTimeMs": 15669.449234,
      "durationMs": 3.239250999999058,
      "memoryEndMB": 382.5
    },
    {
      "kind": "layout",
      "name": "MarketingDefaultLocaleLayout",
      "path": "src/app/(marketing)/(default)/layout.tsx",
      "route": "/",
      "phase": "layout",
      "meta": {
        "moduleType": "layout",
        "segmentGroups": [
          "marketing",
          "default"
        ]
      },
      "id": "layout:14",
      "startTimeMs": 15667.544625,
      "memoryStartMB": 382.5,
      "endTimeMs": 17482.261571,
      "durationMs": 1814.7169459999986,
      "memoryEndMB": 408.31
    },
    {
      "kind": "layout",
      "name": "MarketingGroupLayout",
      "path": "src/app/(marketing)/layout.tsx",
      "route": "/",
      "phase": "layout",
      "meta": {
        "moduleType": "layout",
        "segmentGroups": [
          "marketing"
        ]
      },
      "id": "layout:15",
      "startTimeMs": 15712.674828,
      "memoryStartMB": 383,
      "endTimeMs": 15724.646088,
      "durationMs": 11.971260000000257,
      "memoryEndMB": 383.13
    },
    {
      "kind": "layout",
      "name": "MarketingDefaultLocaleLayout",
      "path": "src/app/(marketing)/(default)/layout.tsx",
      "route": "/",
      "phase": "layout",
      "meta": {
        "moduleType": "layout",
        "segmentGroups": [
          "marketing",
          "default"
        ]
      },
      "id": "layout:16",
      "startTimeMs": 15719.530442,
      "memoryStartMB": 383.13,
      "endTimeMs": 17482.733494,
      "durationMs": 1763.2030520000008,
      "memoryEndMB": 408.31
    },
    {
      "kind": "layout",
      "name": "MarketingGroupLayout",
      "path": "src/app/(marketing)/layout.tsx",
      "route": "/",
      "phase": "layout",
      "meta": {
        "moduleType": "layout",
        "segmentGroups": [
          "marketing"
        ]
      },
      "id": "layout:17",
      "startTimeMs": 18660.603127,
      "memoryStartMB": 437.15,
      "endTimeMs": 18663.350788,
      "durationMs": 2.7476610000012442,
      "memoryEndMB": 437.15
    },
    {
      "kind": "layout",
      "name": "MarketingDefaultLocaleLayout",
      "path": "src/app/(marketing)/(default)/layout.tsx",
      "route": "/",
      "phase": "layout",
      "meta": {
        "moduleType": "layout",
        "segmentGroups": [
          "marketing",
          "default"
        ]
      },
      "id": "layout:18",
      "startTimeMs": 18661.583482,
      "memoryStartMB": 437.15,
      "endTimeMs": 18755.574691,
      "durationMs": 93.99120900000344,
      "memoryEndMB": 437.9
    },
    {
      "kind": "layout",
      "name": "MarketingGroupLayout",
      "path": "src/app/(marketing)/layout.tsx",
      "route": "/",
      "phase": "layout",
      "meta": {
        "moduleType": "layout",
        "segmentGroups": [
          "marketing"
        ]
      },
      "id": "layout:19",
      "startTimeMs": 18997.608296,
      "memoryStartMB": 433.95,
      "endTimeMs": 19000.142588,
      "durationMs": 2.5342920000002778,
      "memoryEndMB": 433.95
    },
    {
      "kind": "layout",
      "name": "MarketingDefaultLocaleLayout",
      "path": "src/app/(marketing)/(default)/layout.tsx",
      "route": "/",
      "phase": "layout",
      "meta": {
        "moduleType": "layout",
        "segmentGroups": [
          "marketing",
          "default"
        ]
      },
      "id": "layout:20",
      "startTimeMs": 18998.656296,
      "memoryStartMB": 433.95,
      "endTimeMs": 19022.241339,
      "durationMs": 23.585042999999132,
      "memoryEndMB": 434.7
    },
    {
      "kind": "layout",
      "name": "MarketingGroupLayout",
      "path": "src/app/(marketing)/layout.tsx",
      "route": "/",
      "phase": "layout",
      "meta": {
        "moduleType": "layout",
        "segmentGroups": [
          "marketing"
        ]
      },
      "id": "layout:21",
      "startTimeMs": 19111.030657,
      "memoryStartMB": 432.4,
      "endTimeMs": 19113.364454,
      "durationMs": 2.333796999999322,
      "memoryEndMB": 432.4
    },
    {
      "kind": "layout",
      "name": "MarketingDefaultLocaleLayout",
      "path": "src/app/(marketing)/(default)/layout.tsx",
      "route": "/",
      "phase": "layout",
      "meta": {
        "moduleType": "layout",
        "segmentGroups": [
          "marketing",
          "default"
        ]
      },
      "id": "layout:22",
      "startTimeMs": 19112.133274,
      "memoryStartMB": 432.4,
      "endTimeMs": 19132.607708,
      "durationMs": 20.474433999999746,
      "memoryEndMB": 433.15
    },
    {
      "kind": "layout",
      "name": "MarketingGroupLayout",
      "path": "src/app/(marketing)/layout.tsx",
      "route": "/",
      "phase": "layout",
      "meta": {
        "moduleType": "layout",
        "segmentGroups": [
          "marketing"
        ]
      },
      "id": "layout:23",
      "startTimeMs": 19207.298961,
      "memoryStartMB": 435.78,
      "endTimeMs": 19218.019131,
      "durationMs": 10.720170000000508,
      "memoryEndMB": 435.78
    },
    {
      "kind": "layout",
      "name": "MarketingDefaultLocaleLayout",
      "path": "src/app/(marketing)/(default)/layout.tsx",
      "route": "/",
      "phase": "layout",
      "meta": {
        "moduleType": "layout",
        "segmentGroups": [
          "marketing",
          "default"
        ]
      },
      "id": "layout:24",
      "startTimeMs": 19216.095993,
      "memoryStartMB": 435.78,
      "endTimeMs": 19239.288223,
      "durationMs": 23.192230000000563,
      "memoryEndMB": 436.53
    },
    {
      "kind": "layout",
      "name": "MarketingGroupLayout",
      "path": "src/app/(marketing)/layout.tsx",
      "route": "/",
      "phase": "layout",
      "meta": {
        "moduleType": "layout",
        "segmentGroups": [
          "marketing"
        ]
      },
      "id": "layout:25",
      "startTimeMs": 19357.974155,
      "memoryStartMB": 436.79,
      "endTimeMs": 19360.629467,
      "durationMs": 2.6553119999989576,
      "memoryEndMB": 436.79
    },
    {
      "kind": "layout",
      "name": "MarketingDefaultLocaleLayout",
      "path": "src/app/(marketing)/(default)/layout.tsx",
      "route": "/",
      "phase": "layout",
      "meta": {
        "moduleType": "layout",
        "segmentGroups": [
          "marketing",
          "default"
        ]
      },
      "id": "layout:26",
      "startTimeMs": 19359.008533,
      "memoryStartMB": 436.79,
      "endTimeMs": 19386.588577,
      "durationMs": 27.580043999998452,
      "memoryEndMB": 437.54
    },
    {
      "kind": "layout",
      "name": "MarketingGroupLayout",
      "path": "src/app/(marketing)/layout.tsx",
      "route": "/",
      "phase": "layout",
      "meta": {
        "moduleType": "layout",
        "segmentGroups": [
          "marketing"
        ]
      },
      "id": "layout:27",
      "startTimeMs": 19466.026872,
      "memoryStartMB": 440.29,
      "endTimeMs": 19468.927637,
      "durationMs": 2.9007650000021385,
      "memoryEndMB": 440.29
    },
    {
      "kind": "layout",
      "name": "MarketingDefaultLocaleLayout",
      "path": "src/app/(marketing)/(default)/layout.tsx",
      "route": "/",
      "phase": "layout",
      "meta": {
        "moduleType": "layout",
        "segmentGroups": [
          "marketing",
          "default"
        ]
      },
      "id": "layout:28",
      "startTimeMs": 19467.177026,
      "memoryStartMB": 440.29,
      "endTimeMs": 19533.767709,
      "durationMs": 66.59068299999853,
      "memoryEndMB": 441.04
    },
    {
      "kind": "layout",
      "name": "MarketingGroupLayout",
      "path": "src/app/(marketing)/layout.tsx",
      "route": "/",
      "phase": "layout",
      "meta": {
        "moduleType": "layout",
        "segmentGroups": [
          "marketing"
        ]
      },
      "id": "layout:29",
      "startTimeMs": 19782.900882,
      "memoryStartMB": 441.89,
      "endTimeMs": 19790.179934,
      "durationMs": 7.279051999998046,
      "memoryEndMB": 441.89
    },
    {
      "kind": "layout",
      "name": "MarketingDefaultLocaleLayout",
      "path": "src/app/(marketing)/(default)/layout.tsx",
      "route": "/",
      "phase": "layout",
      "meta": {
        "moduleType": "layout",
        "segmentGroups": [
          "marketing",
          "default"
        ]
      },
      "id": "layout:30",
      "startTimeMs": 19784.27337,
      "memoryStartMB": 441.89,
      "endTimeMs": 19811.664468,
      "durationMs": 27.391098000000056,
      "memoryEndMB": 442.64
    },
    {
      "kind": "layout",
      "name": "MarketingGroupLayout",
      "path": "src/app/(marketing)/layout.tsx",
      "route": "/",
      "phase": "layout",
      "meta": {
        "moduleType": "layout",
        "segmentGroups": [
          "marketing"
        ]
      },
      "id": "layout:31",
      "startTimeMs": 19905.627014,
      "memoryStartMB": 445.39,
      "endTimeMs": 19907.893765,
      "durationMs": 2.2667509999992035,
      "memoryEndMB": 445.39
    },
    {
      "kind": "layout",
      "name": "MarketingDefaultLocaleLayout",
      "path": "src/app/(marketing)/(default)/layout.tsx",
      "route": "/",
      "phase": "layout",
      "meta": {
        "moduleType": "layout",
        "segmentGroups": [
          "marketing",
          "default"
        ]
      },
      "id": "layout:32",
      "startTimeMs": 19906.592374,
      "memoryStartMB": 445.39,
      "endTimeMs": 19952.15681,
      "durationMs": 45.56443600000057,
      "memoryEndMB": 446.39
    },
    {
      "kind": "layout",
      "name": "MarketingGroupLayout",
      "path": "src/app/(marketing)/layout.tsx",
      "route": "/",
      "phase": "layout",
      "meta": {
        "moduleType": "layout",
        "segmentGroups": [
          "marketing"
        ]
      },
      "id": "layout:33",
      "startTimeMs": 21229.807195,
      "memoryStartMB": 473.89,
      "endTimeMs": 21235.793776,
      "durationMs": 5.986580999997386,
      "memoryEndMB": 473.89
    },
    {
      "kind": "layout",
      "name": "MarketingDefaultLocaleLayout",
      "path": "src/app/(marketing)/(default)/layout.tsx",
      "route": "/",
      "phase": "layout",
      "meta": {
        "moduleType": "layout",
        "segmentGroups": [
          "marketing",
          "default"
        ]
      },
      "id": "layout:34",
      "startTimeMs": 21230.849166,
      "memoryStartMB": 473.89,
      "endTimeMs": 21258.763755,
      "durationMs": 27.914588999999978,
      "memoryEndMB": 474.64
    },
    {
      "kind": "layout",
      "name": "MarketingGroupLayout",
      "path": "src/app/(marketing)/layout.tsx",
      "route": "/",
      "phase": "layout",
      "meta": {
        "moduleType": "layout",
        "segmentGroups": [
          "marketing"
        ]
      },
      "id": "layout:35",
      "startTimeMs": 21378.365327,
      "memoryStartMB": 470.18,
      "endTimeMs": 21390.895801,
      "durationMs": 12.53047399999923,
      "memoryEndMB": 470.18
    },
    {
      "kind": "layout",
      "name": "MarketingDefaultLocaleLayout",
      "path": "src/app/(marketing)/(default)/layout.tsx",
      "route": "/",
      "phase": "layout",
      "meta": {
        "moduleType": "layout",
        "segmentGroups": [
          "marketing",
          "default"
        ]
      },
      "id": "layout:36",
      "startTimeMs": 21379.788884,
      "memoryStartMB": 470.18,
      "endTimeMs": 21413.477452,
      "durationMs": 33.68856799999776,
      "memoryEndMB": 470.93
    },
    {
      "kind": "layout",
      "name": "MarketingGroupLayout",
      "path": "src/app/(marketing)/layout.tsx",
      "route": "/",
      "phase": "layout",
      "meta": {
        "moduleType": "layout",
        "segmentGroups": [
          "marketing"
        ]
      },
      "id": "layout:37",
      "startTimeMs": 21499.982058,
      "memoryStartMB": 473.68,
      "endTimeMs": 21503.725008,
      "durationMs": 3.742949999999837,
      "memoryEndMB": 473.68
    },
    {
      "kind": "layout",
      "name": "MarketingDefaultLocaleLayout",
      "path": "src/app/(marketing)/(default)/layout.tsx",
      "route": "/",
      "phase": "layout",
      "meta": {
        "moduleType": "layout",
        "segmentGroups": [
          "marketing",
          "default"
        ]
      },
      "id": "layout:38",
      "startTimeMs": 21500.962679,
      "memoryStartMB": 473.68,
      "endTimeMs": 21524.727547,
      "durationMs": 23.764867999998387,
      "memoryEndMB": 474.43
    },
    {
      "kind": "layout",
      "name": "MarketingGroupLayout",
      "path": "src/app/(marketing)/layout.tsx",
      "route": "/",
      "phase": "layout",
      "meta": {
        "moduleType": "layout",
        "segmentGroups": [
          "marketing"
        ]
      },
      "id": "layout:39",
      "startTimeMs": 21578.500724,
      "memoryStartMB": 474.93,
      "endTimeMs": 21583.653443,
      "durationMs": 5.152718999997887,
      "memoryEndMB": 474.93
    },
    {
      "kind": "layout",
      "name": "MarketingDefaultLocaleLayout",
      "path": "src/app/(marketing)/(default)/layout.tsx",
      "route": "/",
      "phase": "layout",
      "meta": {
        "moduleType": "layout",
        "segmentGroups": [
          "marketing",
          "default"
        ]
      },
      "id": "layout:40",
      "startTimeMs": 21579.48178,
      "memoryStartMB": 474.93,
      "endTimeMs": 21599.655598,
      "durationMs": 20.17381800000294,
      "memoryEndMB": 475.68
    },
    {
      "kind": "layout",
      "name": "MarketingGroupLayout",
      "path": "src/app/(marketing)/layout.tsx",
      "route": "/",
      "phase": "layout",
      "meta": {
        "moduleType": "layout",
        "segmentGroups": [
          "marketing"
        ]
      },
      "id": "layout:41",
      "startTimeMs": 21664.265516,
      "memoryStartMB": 478.3,
      "endTimeMs": 21667.332796,
      "durationMs": 3.0672799999993003,
      "memoryEndMB": 478.3
    },
    {
      "kind": "layout",
      "name": "MarketingDefaultLocaleLayout",
      "path": "src/app/(marketing)/(default)/layout.tsx",
      "route": "/",
      "phase": "layout",
      "meta": {
        "moduleType": "layout",
        "segmentGroups": [
          "marketing",
          "default"
        ]
      },
      "id": "layout:42",
      "startTimeMs": 21665.039595,
      "memoryStartMB": 478.3,
      "endTimeMs": 21704.354911,
      "durationMs": 39.315316000000166,
      "memoryEndMB": 479.05
    },
    {
      "kind": "layout",
      "name": "MarketingGroupLayout",
      "path": "src/app/(marketing)/layout.tsx",
      "route": "/",
      "phase": "layout",
      "meta": {
        "moduleType": "layout",
        "segmentGroups": [
          "marketing"
        ]
      },
      "id": "layout:43",
      "startTimeMs": 21768.530604,
      "memoryStartMB": 481.8,
      "endTimeMs": 21772.952229,
      "durationMs": 4.42162499999904,
      "memoryEndMB": 481.8
    },
    {
      "kind": "layout",
      "name": "MarketingDefaultLocaleLayout",
      "path": "src/app/(marketing)/(default)/layout.tsx",
      "route": "/",
      "phase": "layout",
      "meta": {
        "moduleType": "layout",
        "segmentGroups": [
          "marketing",
          "default"
        ]
      },
      "id": "layout:44",
      "startTimeMs": 21769.832759,
      "memoryStartMB": 481.8,
      "endTimeMs": 21818.299584,
      "durationMs": 48.46682499999952,
      "memoryEndMB": 477.45
    },
    {
      "kind": "layout",
      "name": "MarketingGroupLayout",
      "path": "src/app/(marketing)/layout.tsx",
      "route": "/",
      "phase": "layout",
      "meta": {
        "moduleType": "layout",
        "segmentGroups": [
          "marketing"
        ]
      },
      "id": "layout:45",
      "startTimeMs": 21908.389543,
      "memoryStartMB": 480.08,
      "endTimeMs": 21913.160541,
      "durationMs": 4.770997999999963,
      "memoryEndMB": 480.2
    },
    {
      "kind": "layout",
      "name": "MarketingDefaultLocaleLayout",
      "path": "src/app/(marketing)/(default)/layout.tsx",
      "route": "/",
      "phase": "layout",
      "meta": {
        "moduleType": "layout",
        "segmentGroups": [
          "marketing",
          "default"
        ]
      },
      "id": "layout:46",
      "startTimeMs": 21909.466631,
      "memoryStartMB": 480.08,
      "endTimeMs": 21930.013305,
      "durationMs": 20.546674000001076,
      "memoryEndMB": 480.83
    },
    {
      "kind": "layout",
      "name": "MarketingGroupLayout",
      "path": "src/app/(marketing)/layout.tsx",
      "route": "/",
      "phase": "layout",
      "meta": {
        "moduleType": "layout",
        "segmentGroups": [
          "marketing"
        ]
      },
      "id": "layout:47",
      "startTimeMs": 22027.678414,
      "memoryStartMB": 484.2,
      "endTimeMs": 22032.167024,
      "durationMs": 4.488609999996697,
      "memoryEndMB": 484.2
    },
    {
      "kind": "layout",
      "name": "MarketingDefaultLocaleLayout",
      "path": "src/app/(marketing)/(default)/layout.tsx",
      "route": "/",
      "phase": "layout",
      "meta": {
        "moduleType": "layout",
        "segmentGroups": [
          "marketing",
          "default"
        ]
      },
      "id": "layout:48",
      "startTimeMs": 22029.154019,
      "memoryStartMB": 484.2,
      "endTimeMs": 22092.956574,
      "durationMs": 63.80255499999839,
      "memoryEndMB": 480.59
    },
    {
      "kind": "layout",
      "name": "MarketingGroupLayout",
      "path": "src/app/(marketing)/layout.tsx",
      "route": "/",
      "phase": "layout",
      "meta": {
        "moduleType": "layout",
        "segmentGroups": [
          "marketing"
        ]
      },
      "id": "layout:49",
      "startTimeMs": 22948.714546,
      "memoryStartMB": 520.42,
      "endTimeMs": 22951.72186,
      "durationMs": 3.007314000002225,
      "memoryEndMB": 520.42
    },
    {
      "kind": "layout",
      "name": "MarketingDefaultLocaleLayout",
      "path": "src/app/(marketing)/(default)/layout.tsx",
      "route": "/",
      "phase": "layout",
      "meta": {
        "moduleType": "layout",
        "segmentGroups": [
          "marketing",
          "default"
        ]
      },
      "id": "layout:50",
      "startTimeMs": 22949.857527,
      "memoryStartMB": 520.42,
      "endTimeMs": 22968.849249,
      "durationMs": 18.991721999998845,
      "memoryEndMB": 521.17
    },
    {
      "kind": "layout",
      "name": "MarketingGroupLayout",
      "path": "src/app/(marketing)/layout.tsx",
      "route": "/",
      "phase": "layout",
      "meta": {
        "moduleType": "layout",
        "segmentGroups": [
          "marketing"
        ]
      },
      "id": "layout:51",
      "startTimeMs": 23024.856944,
      "memoryStartMB": 513.39,
      "endTimeMs": 23029.398794,
      "durationMs": 4.541850000001432,
      "memoryEndMB": 513.39
    },
    {
      "kind": "layout",
      "name": "MarketingDefaultLocaleLayout",
      "path": "src/app/(marketing)/(default)/layout.tsx",
      "route": "/",
      "phase": "layout",
      "meta": {
        "moduleType": "layout",
        "segmentGroups": [
          "marketing",
          "default"
        ]
      },
      "id": "layout:52",
      "startTimeMs": 23025.827084,
      "memoryStartMB": 513.39,
      "endTimeMs": 23055.413488,
      "durationMs": 29.586403999997856,
      "memoryEndMB": 514.14
    },
    {
      "kind": "layout",
      "name": "MarketingGroupLayout",
      "path": "src/app/(marketing)/layout.tsx",
      "route": "/",
      "phase": "layout",
      "meta": {
        "moduleType": "layout",
        "segmentGroups": [
          "marketing"
        ]
      },
      "id": "layout:53",
      "startTimeMs": 23173.822147,
      "memoryStartMB": 517.52,
      "endTimeMs": 23176.714885,
      "durationMs": 2.892738000002282,
      "memoryEndMB": 517.52
    },
    {
      "kind": "layout",
      "name": "MarketingDefaultLocaleLayout",
      "path": "src/app/(marketing)/(default)/layout.tsx",
      "route": "/",
      "phase": "layout",
      "meta": {
        "moduleType": "layout",
        "segmentGroups": [
          "marketing",
          "default"
        ]
      },
      "id": "layout:54",
      "startTimeMs": 23174.868313,
      "memoryStartMB": 517.52,
      "endTimeMs": 23196.950127,
      "durationMs": 22.08181400000103,
      "memoryEndMB": 518.27
    },
    {
      "kind": "layout",
      "name": "MarketingGroupLayout",
      "path": "src/app/(marketing)/layout.tsx",
      "route": "/",
      "phase": "layout",
      "meta": {
        "moduleType": "layout",
        "segmentGroups": [
          "marketing"
        ]
      },
      "id": "layout:55",
      "startTimeMs": 23252.419452,
      "memoryStartMB": 520.89,
      "endTimeMs": 23255.10191,
      "durationMs": 2.6824580000029528,
      "memoryEndMB": 520.89
    },
    {
      "kind": "layout",
      "name": "MarketingDefaultLocaleLayout",
      "path": "src/app/(marketing)/(default)/layout.tsx",
      "route": "/",
      "phase": "layout",
      "meta": {
        "moduleType": "layout",
        "segmentGroups": [
          "marketing",
          "default"
        ]
      },
      "id": "layout:56",
      "startTimeMs": 23253.715984,
      "memoryStartMB": 520.89,
      "endTimeMs": 23286.826844,
      "durationMs": 33.110860000000685,
      "memoryEndMB": 516.4
    },
    {
      "kind": "layout",
      "name": "MarketingGroupLayout",
      "path": "src/app/(marketing)/layout.tsx",
      "route": "/",
      "phase": "layout",
      "meta": {
        "moduleType": "layout",
        "segmentGroups": [
          "marketing"
        ]
      },
      "id": "layout:57",
      "startTimeMs": 23339.119679,
      "memoryStartMB": 519.4,
      "endTimeMs": 23341.376289,
      "durationMs": 2.2566100000003644,
      "memoryEndMB": 519.4
    },
    {
      "kind": "layout",
      "name": "MarketingDefaultLocaleLayout",
      "path": "src/app/(marketing)/(default)/layout.tsx",
      "route": "/",
      "phase": "layout",
      "meta": {
        "moduleType": "layout",
        "segmentGroups": [
          "marketing",
          "default"
        ]
      },
      "id": "layout:58",
      "startTimeMs": 23340.048461,
      "memoryStartMB": 519.4,
      "endTimeMs": 23359.500375,
      "durationMs": 19.451914000001125,
      "memoryEndMB": 520.15
    },
    {
      "kind": "layout",
      "name": "MarketingGroupLayout",
      "path": "src/app/(marketing)/layout.tsx",
      "route": "/",
      "phase": "layout",
      "meta": {
        "moduleType": "layout",
        "segmentGroups": [
          "marketing"
        ]
      },
      "id": "layout:59",
      "startTimeMs": 23440.885399,
      "memoryStartMB": 523.52,
      "endTimeMs": 23472.440239,
      "durationMs": 31.554840000000695,
      "memoryEndMB": 522.2
    },
    {
      "kind": "layout",
      "name": "MarketingDefaultLocaleLayout",
      "path": "src/app/(marketing)/(default)/layout.tsx",
      "route": "/",
      "phase": "layout",
      "meta": {
        "moduleType": "layout",
        "segmentGroups": [
          "marketing",
          "default"
        ]
      },
      "id": "layout:60",
      "startTimeMs": 23441.821099,
      "memoryStartMB": 523.52,
      "endTimeMs": 23493.900066,
      "durationMs": 52.07896699999765,
      "memoryEndMB": 520.28
    },
    {
      "kind": "layout",
      "name": "MarketingGroupLayout",
      "path": "src/app/(marketing)/layout.tsx",
      "route": "/",
      "phase": "layout",
      "meta": {
        "moduleType": "layout",
        "segmentGroups": [
          "marketing"
        ]
      },
      "id": "layout:61",
      "startTimeMs": 23557.089029,
      "memoryStartMB": 523.91,
      "endTimeMs": 23559.973744,
      "durationMs": 2.884715000000142,
      "memoryEndMB": 523.91
    },
    {
      "kind": "layout",
      "name": "MarketingDefaultLocaleLayout",
      "path": "src/app/(marketing)/(default)/layout.tsx",
      "route": "/",
      "phase": "layout",
      "meta": {
        "moduleType": "layout",
        "segmentGroups": [
          "marketing",
          "default"
        ]
      },
      "id": "layout:62",
      "startTimeMs": 23558.610712,
      "memoryStartMB": 523.91,
      "endTimeMs": 23579.378707,
      "durationMs": 20.767994999998336,
      "memoryEndMB": 525.53
    },
    {
      "kind": "layout",
      "name": "MarketingGroupLayout",
      "path": "src/app/(marketing)/layout.tsx",
      "route": "/",
      "phase": "layout",
      "meta": {
        "moduleType": "layout",
        "segmentGroups": [
          "marketing"
        ]
      },
      "id": "layout:63",
      "startTimeMs": 23762.747913,
      "memoryStartMB": 529.41,
      "endTimeMs": 23765.185101,
      "durationMs": 2.4371879999998782,
      "memoryEndMB": 529.41
    },
    {
      "kind": "layout",
      "name": "MarketingDefaultLocaleLayout",
      "path": "src/app/(marketing)/(default)/layout.tsx",
      "route": "/",
      "phase": "layout",
      "meta": {
        "moduleType": "layout",
        "segmentGroups": [
          "marketing",
          "default"
        ]
      },
      "id": "layout:64",
      "startTimeMs": 23763.687998,
      "memoryStartMB": 529.41,
      "endTimeMs": 23784.026244,
      "durationMs": 20.338245999999344,
      "memoryEndMB": 530.16
    },
    {
      "kind": "layout",
      "name": "MarketingGroupLayout",
      "path": "src/app/(marketing)/layout.tsx",
      "route": "/",
      "phase": "layout",
      "meta": {
        "moduleType": "layout",
        "segmentGroups": [
          "marketing"
        ]
      },
      "id": "layout:65",
      "startTimeMs": 24751.589055,
      "memoryStartMB": 562.22,
      "endTimeMs": 24753.940414,
      "durationMs": 2.3513590000002296,
      "memoryEndMB": 562.22
    },
    {
      "kind": "layout",
      "name": "MarketingDefaultLocaleLayout",
      "path": "src/app/(marketing)/(default)/layout.tsx",
      "route": "/",
      "phase": "layout",
      "meta": {
        "moduleType": "layout",
        "segmentGroups": [
          "marketing",
          "default"
        ]
      },
      "id": "layout:66",
      "startTimeMs": 24752.556214,
      "memoryStartMB": 562.22,
      "endTimeMs": 24773.642677,
      "durationMs": 21.08646299999964,
      "memoryEndMB": 562.97
    },
    {
      "kind": "layout",
      "name": "MarketingGroupLayout",
      "path": "src/app/(marketing)/layout.tsx",
      "route": "/",
      "phase": "layout",
      "meta": {
        "moduleType": "layout",
        "segmentGroups": [
          "marketing"
        ]
      },
      "id": "layout:67",
      "startTimeMs": 24897.268642,
      "memoryStartMB": 567.22,
      "endTimeMs": 24899.751995,
      "durationMs": 2.4833529999996244,
      "memoryEndMB": 567.22
    },
    {
      "kind": "layout",
      "name": "MarketingDefaultLocaleLayout",
      "path": "src/app/(marketing)/(default)/layout.tsx",
      "route": "/",
      "phase": "layout",
      "meta": {
        "moduleType": "layout",
        "segmentGroups": [
          "marketing",
          "default"
        ]
      },
      "id": "layout:68",
      "startTimeMs": 24898.445876,
      "memoryStartMB": 567.22,
      "endTimeMs": 24947.586673,
      "durationMs": 49.14079700000002,
      "memoryEndMB": 561.37
    },
    {
      "kind": "layout",
      "name": "MarketingGroupLayout",
      "path": "src/app/(marketing)/layout.tsx",
      "route": "/",
      "phase": "layout",
      "meta": {
        "moduleType": "layout",
        "segmentGroups": [
          "marketing"
        ]
      },
      "id": "layout:69",
      "startTimeMs": 25013.369114,
      "memoryStartMB": 563.99,
      "endTimeMs": 25016.372177,
      "durationMs": 3.003063000000111,
      "memoryEndMB": 564.12
    },
    {
      "kind": "layout",
      "name": "MarketingDefaultLocaleLayout",
      "path": "src/app/(marketing)/(default)/layout.tsx",
      "route": "/",
      "phase": "layout",
      "meta": {
        "moduleType": "layout",
        "segmentGroups": [
          "marketing",
          "default"
        ]
      },
      "id": "layout:70",
      "startTimeMs": 25014.399036,
      "memoryStartMB": 563.99,
      "endTimeMs": 25041.49239,
      "durationMs": 27.093354000000545,
      "memoryEndMB": 564.87
    },
    {
      "kind": "layout",
      "name": "MarketingGroupLayout",
      "path": "src/app/(marketing)/layout.tsx",
      "route": "/",
      "phase": "layout",
      "meta": {
        "moduleType": "layout",
        "segmentGroups": [
          "marketing"
        ]
      },
      "id": "layout:71",
      "startTimeMs": 25132.39211,
      "memoryStartMB": 565.09,
      "endTimeMs": 25142.497459,
      "durationMs": 10.10534899999766,
      "memoryEndMB": 565.09
    },
    {
      "kind": "layout",
      "name": "MarketingDefaultLocaleLayout",
      "path": "src/app/(marketing)/(default)/layout.tsx",
      "route": "/",
      "phase": "layout",
      "meta": {
        "moduleType": "layout",
        "segmentGroups": [
          "marketing",
          "default"
        ]
      },
      "id": "layout:72",
      "startTimeMs": 25138.397578,
      "memoryStartMB": 565.09,
      "endTimeMs": 25178.871888,
      "durationMs": 40.474310000001424,
      "memoryEndMB": 565.84
    },
    {
      "kind": "layout",
      "name": "MarketingGroupLayout",
      "path": "src/app/(marketing)/layout.tsx",
      "route": "/",
      "phase": "layout",
      "meta": {
        "moduleType": "layout",
        "segmentGroups": [
          "marketing"
        ]
      },
      "id": "layout:73",
      "startTimeMs": 25273.808521,
      "memoryStartMB": 569.22,
      "endTimeMs": 25276.883382,
      "durationMs": 3.074861000000965,
      "memoryEndMB": 569.22
    },
    {
      "kind": "layout",
      "name": "MarketingDefaultLocaleLayout",
      "path": "src/app/(marketing)/(default)/layout.tsx",
      "route": "/",
      "phase": "layout",
      "meta": {
        "moduleType": "layout",
        "segmentGroups": [
          "marketing",
          "default"
        ]
      },
      "id": "layout:74",
      "startTimeMs": 25275.092748,
      "memoryStartMB": 569.22,
      "endTimeMs": 25295.859697,
      "durationMs": 20.76694900000075,
      "memoryEndMB": 569.97
    },
    {
      "kind": "layout",
      "name": "MarketingGroupLayout",
      "path": "src/app/(marketing)/layout.tsx",
      "route": "/",
      "phase": "layout",
      "meta": {
        "moduleType": "layout",
        "segmentGroups": [
          "marketing"
        ]
      },
      "id": "layout:75",
      "startTimeMs": 25407.143398,
      "memoryStartMB": 570.87,
      "endTimeMs": 25411.829667,
      "durationMs": 4.68626900000163,
      "memoryEndMB": 571.12
    },
    {
      "kind": "layout",
      "name": "MarketingDefaultLocaleLayout",
      "path": "src/app/(marketing)/(default)/layout.tsx",
      "route": "/",
      "phase": "layout",
      "meta": {
        "moduleType": "layout",
        "segmentGroups": [
          "marketing",
          "default"
        ]
      },
      "id": "layout:76",
      "startTimeMs": 25410.088765,
      "memoryStartMB": 570.87,
      "endTimeMs": 25436.877594,
      "durationMs": 26.788829000000987,
      "memoryEndMB": 572.5
    },
    {
      "kind": "layout",
      "name": "MarketingGroupLayout",
      "path": "src/app/(marketing)/layout.tsx",
      "route": "/",
      "phase": "layout",
      "meta": {
        "moduleType": "layout",
        "segmentGroups": [
          "marketing"
        ]
      },
      "id": "layout:77",
      "startTimeMs": 25507.143087,
      "memoryStartMB": 578.25,
      "endTimeMs": 25515.415729,
      "durationMs": 8.272641999999905,
      "memoryEndMB": 578.37
    },
    {
      "kind": "layout",
      "name": "MarketingDefaultLocaleLayout",
      "path": "src/app/(marketing)/(default)/layout.tsx",
      "route": "/",
      "phase": "layout",
      "meta": {
        "moduleType": "layout",
        "segmentGroups": [
          "marketing",
          "default"
        ]
      },
      "id": "layout:78",
      "startTimeMs": 25508.18503,
      "memoryStartMB": 578.37,
      "endTimeMs": 25539.147208,
      "durationMs": 30.962177999997948,
      "memoryEndMB": 579.25
    },
    {
      "kind": "layout",
      "name": "MarketingGroupLayout",
      "path": "src/app/(marketing)/layout.tsx",
      "route": "/",
      "phase": "layout",
      "meta": {
        "moduleType": "layout",
        "segmentGroups": [
          "marketing"
        ]
      },
      "id": "layout:79",
      "startTimeMs": 25625.816178,
      "memoryStartMB": 582.01,
      "endTimeMs": 25628.515253,
      "durationMs": 2.699075000000448,
      "memoryEndMB": 582.01
    },
    {
      "kind": "layout",
      "name": "MarketingDefaultLocaleLayout",
      "path": "src/app/(marketing)/(default)/layout.tsx",
      "route": "/",
      "phase": "layout",
      "meta": {
        "moduleType": "layout",
        "segmentGroups": [
          "marketing",
          "default"
        ]
      },
      "id": "layout:80",
      "startTimeMs": 25626.99401,
      "memoryStartMB": 582.01,
      "endTimeMs": 25661.007823,
      "durationMs": 34.01381300000139,
      "memoryEndMB": 582.88
    },
    {
      "kind": "layout",
      "name": "MarketingGroupLayout",
      "path": "src/app/(marketing)/layout.tsx",
      "route": "/",
      "phase": "layout",
      "meta": {
        "moduleType": "layout",
        "segmentGroups": [
          "marketing"
        ]
      },
      "id": "layout:81",
      "startTimeMs": 26441.233726,
      "memoryStartMB": 620.03,
      "endTimeMs": 26454.919606,
      "durationMs": 13.685880000000907,
      "memoryEndMB": 620.03
    },
    {
      "kind": "layout",
      "name": "MarketingDefaultLocaleLayout",
      "path": "src/app/(marketing)/(default)/layout.tsx",
      "route": "/",
      "phase": "layout",
      "meta": {
        "moduleType": "layout",
        "segmentGroups": [
          "marketing",
          "default"
        ]
      },
      "id": "layout:82",
      "startTimeMs": 26442.221747,
      "memoryStartMB": 620.03,
      "endTimeMs": 26478.072036,
      "durationMs": 35.850289000001794,
      "memoryEndMB": 620.78
    },
    {
      "kind": "layout",
      "name": "MarketingGroupLayout",
      "path": "src/app/(marketing)/layout.tsx",
      "route": "/",
      "phase": "layout",
      "meta": {
        "moduleType": "layout",
        "segmentGroups": [
          "marketing"
        ]
      },
      "id": "layout:83",
      "startTimeMs": 26562.340766,
      "memoryStartMB": 614.03,
      "endTimeMs": 26564.613154,
      "durationMs": 2.2723879999975907,
      "memoryEndMB": 614.03
    },
    {
      "kind": "layout",
      "name": "MarketingDefaultLocaleLayout",
      "path": "src/app/(marketing)/(default)/layout.tsx",
      "route": "/",
      "phase": "layout",
      "meta": {
        "moduleType": "layout",
        "segmentGroups": [
          "marketing",
          "default"
        ]
      },
      "id": "layout:84",
      "startTimeMs": 26563.303616,
      "memoryStartMB": 614.03,
      "endTimeMs": 26583.906275,
      "durationMs": 20.60265900000013,
      "memoryEndMB": 614.66
    },
    {
      "kind": "layout",
      "name": "MarketingGroupLayout",
      "path": "src/app/(marketing)/layout.tsx",
      "route": "/",
      "phase": "layout",
      "meta": {
        "moduleType": "layout",
        "segmentGroups": [
          "marketing"
        ]
      },
      "id": "layout:85",
      "startTimeMs": 26659.446888,
      "memoryStartMB": 617.28,
      "endTimeMs": 26663.73415,
      "durationMs": 4.287262000001647,
      "memoryEndMB": 617.28
    },
    {
      "kind": "layout",
      "name": "MarketingDefaultLocaleLayout",
      "path": "src/app/(marketing)/(default)/layout.tsx",
      "route": "/",
      "phase": "layout",
      "meta": {
        "moduleType": "layout",
        "segmentGroups": [
          "marketing",
          "default"
        ]
      },
      "id": "layout:86",
      "startTimeMs": 26662.433941,
      "memoryStartMB": 617.28,
      "endTimeMs": 26699.29857,
      "durationMs": 36.864628999999695,
      "memoryEndMB": 617.91
    },
    {
      "kind": "layout",
      "name": "MarketingGroupLayout",
      "path": "src/app/(marketing)/layout.tsx",
      "route": "/",
      "phase": "layout",
      "meta": {
        "moduleType": "layout",
        "segmentGroups": [
          "marketing"
        ]
      },
      "id": "layout:87",
      "startTimeMs": 26810.576721,
      "memoryStartMB": 617.13,
      "endTimeMs": 26812.886982,
      "durationMs": 2.310260999998718,
      "memoryEndMB": 617.13
    },
    {
      "kind": "layout",
      "name": "MarketingDefaultLocaleLayout",
      "path": "src/app/(marketing)/(default)/layout.tsx",
      "route": "/",
      "phase": "layout",
      "meta": {
        "moduleType": "layout",
        "segmentGroups": [
          "marketing",
          "default"
        ]
      },
      "id": "layout:88",
      "startTimeMs": 26811.574442,
      "memoryStartMB": 617.13,
      "endTimeMs": 26831.233698,
      "durationMs": 19.659255999999004,
      "memoryEndMB": 617.88
    },
    {
      "kind": "layout",
      "name": "MarketingGroupLayout",
      "path": "src/app/(marketing)/layout.tsx",
      "route": "/",
      "phase": "layout",
      "meta": {
        "moduleType": "layout",
        "segmentGroups": [
          "marketing"
        ]
      },
      "id": "layout:89",
      "startTimeMs": 26892.574055,
      "memoryStartMB": 622,
      "endTimeMs": 26895.782285,
      "durationMs": 3.208230000000185,
      "memoryEndMB": 622
    },
    {
      "kind": "layout",
      "name": "MarketingDefaultLocaleLayout",
      "path": "src/app/(marketing)/(default)/layout.tsx",
      "route": "/",
      "phase": "layout",
      "meta": {
        "moduleType": "layout",
        "segmentGroups": [
          "marketing",
          "default"
        ]
      },
      "id": "layout:90",
      "startTimeMs": 26893.532083,
      "memoryStartMB": 622,
      "endTimeMs": 26917.775411,
      "durationMs": 24.243328000000474,
      "memoryEndMB": 622.75
    },
    {
      "kind": "layout",
      "name": "MarketingGroupLayout",
      "path": "src/app/(marketing)/layout.tsx",
      "route": "/",
      "phase": "layout",
      "meta": {
        "moduleType": "layout",
        "segmentGroups": [
          "marketing"
        ]
      },
      "id": "layout:91",
      "startTimeMs": 27003.822218,
      "memoryStartMB": 622.43,
      "endTimeMs": 27014.538791,
      "durationMs": 10.71657299999788,
      "memoryEndMB": 622.43
    },
    {
      "kind": "layout",
      "name": "MarketingDefaultLocaleLayout",
      "path": "src/app/(marketing)/(default)/layout.tsx",
      "route": "/",
      "phase": "layout",
      "meta": {
        "moduleType": "layout",
        "segmentGroups": [
          "marketing",
          "default"
        ]
      },
      "id": "layout:92",
      "startTimeMs": 27006.175188,
      "memoryStartMB": 622.43,
      "endTimeMs": 27056.21991,
      "durationMs": 50.04472199999873,
      "memoryEndMB": 623.43
    },
    {
      "kind": "layout",
      "name": "MarketingGroupLayout",
      "path": "src/app/(marketing)/layout.tsx",
      "route": "/",
      "phase": "layout",
      "meta": {
        "moduleType": "layout",
        "segmentGroups": [
          "marketing"
        ]
      },
      "id": "layout:93",
      "startTimeMs": 27151.907887,
      "memoryStartMB": 626.68,
      "endTimeMs": 27155.511595,
      "durationMs": 3.6037079999987327,
      "memoryEndMB": 626.68
    },
    {
      "kind": "layout",
      "name": "MarketingDefaultLocaleLayout",
      "path": "src/app/(marketing)/(default)/layout.tsx",
      "route": "/",
      "phase": "layout",
      "meta": {
        "moduleType": "layout",
        "segmentGroups": [
          "marketing",
          "default"
        ]
      },
      "id": "layout:94",
      "startTimeMs": 27153.19272,
      "memoryStartMB": 626.68,
      "endTimeMs": 27177.902272,
      "durationMs": 24.709552000000258,
      "memoryEndMB": 627.43
    },
    {
      "kind": "layout",
      "name": "MarketingGroupLayout",
      "path": "src/app/(marketing)/layout.tsx",
      "route": "/",
      "phase": "layout",
      "meta": {
        "moduleType": "layout",
        "segmentGroups": [
          "marketing"
        ]
      },
      "id": "layout:95",
      "startTimeMs": 27287.692486,
      "memoryStartMB": 630.07,
      "endTimeMs": 27291.075612,
      "durationMs": 3.3831260000006296,
      "memoryEndMB": 630.07
    },
    {
      "kind": "layout",
      "name": "MarketingDefaultLocaleLayout",
      "path": "src/app/(marketing)/(default)/layout.tsx",
      "route": "/",
      "phase": "layout",
      "meta": {
        "moduleType": "layout",
        "segmentGroups": [
          "marketing",
          "default"
        ]
      },
      "id": "layout:96",
      "startTimeMs": 27288.613127,
      "memoryStartMB": 630.07,
      "endTimeMs": 27340.386717,
      "durationMs": 51.773590000000695,
      "memoryEndMB": 626.09
    },
    {
      "kind": "layout",
      "name": "MarketingGroupLayout",
      "path": "src/app/(marketing)/layout.tsx",
      "route": "/",
      "phase": "layout",
      "meta": {
        "moduleType": "layout",
        "segmentGroups": [
          "marketing"
        ]
      },
      "id": "layout:97",
      "startTimeMs": 28264.482896,
      "memoryStartMB": 677.28,
      "endTimeMs": 28267.412329,
      "durationMs": 2.929432999997516,
      "memoryEndMB": 677.28
    },
    {
      "kind": "layout",
      "name": "MarketingDefaultLocaleLayout",
      "path": "src/app/(marketing)/(default)/layout.tsx",
      "route": "/",
      "phase": "layout",
      "meta": {
        "moduleType": "layout",
        "segmentGroups": [
          "marketing",
          "default"
        ]
      },
      "id": "layout:98",
      "startTimeMs": 28265.668355,
      "memoryStartMB": 677.28,
      "endTimeMs": 28306.735646,
      "durationMs": 41.067290999999386,
      "memoryEndMB": 670.71
    },
    {
      "kind": "layout",
      "name": "MarketingGroupLayout",
      "path": "src/app/(marketing)/layout.tsx",
      "route": "/",
      "phase": "layout",
      "meta": {
        "moduleType": "layout",
        "segmentGroups": [
          "marketing"
        ]
      },
      "id": "layout:99",
      "startTimeMs": 28376.398089,
      "memoryStartMB": 667.07,
      "endTimeMs": 28379.486293,
      "durationMs": 3.0882040000033157,
      "memoryEndMB": 667.07
    },
    {
      "kind": "layout",
      "name": "MarketingDefaultLocaleLayout",
      "path": "src/app/(marketing)/(default)/layout.tsx",
      "route": "/",
      "phase": "layout",
      "meta": {
        "moduleType": "layout",
        "segmentGroups": [
          "marketing",
          "default"
        ]
      },
      "id": "layout:100",
      "startTimeMs": 28377.320236,
      "memoryStartMB": 667.07,
      "endTimeMs": 28396.779589,
      "durationMs": 19.45935300000201,
      "memoryEndMB": 667.82
    },
    {
      "kind": "layout",
      "name": "MarketingGroupLayout",
      "path": "src/app/(marketing)/layout.tsx",
      "route": "/",
      "phase": "layout",
      "meta": {
        "moduleType": "layout",
        "segmentGroups": [
          "marketing"
        ]
      },
      "id": "layout:101",
      "startTimeMs": 28444.895252,
      "memoryStartMB": 670.44,
      "endTimeMs": 28448.823794,
      "durationMs": 3.928542000001471,
      "memoryEndMB": 670.44
    },
    {
      "kind": "layout",
      "name": "MarketingDefaultLocaleLayout",
      "path": "src/app/(marketing)/(default)/layout.tsx",
      "route": "/",
      "phase": "layout",
      "meta": {
        "moduleType": "layout",
        "segmentGroups": [
          "marketing",
          "default"
        ]
      },
      "id": "layout:102",
      "startTimeMs": 28445.860321,
      "memoryStartMB": 670.44,
      "endTimeMs": 28466.297868,
      "durationMs": 20.43754700000136,
      "memoryEndMB": 671.19
    },
    {
      "kind": "layout",
      "name": "MarketingGroupLayout",
      "path": "src/app/(marketing)/layout.tsx",
      "route": "/",
      "phase": "layout",
      "meta": {
        "moduleType": "layout",
        "segmentGroups": [
          "marketing"
        ]
      },
      "id": "layout:103",
      "startTimeMs": 28551.408942,
      "memoryStartMB": 670.38,
      "endTimeMs": 28560.216546,
      "durationMs": 8.807604000001447,
      "memoryEndMB": 670.38
    },
    {
      "kind": "layout",
      "name": "MarketingDefaultLocaleLayout",
      "path": "src/app/(marketing)/(default)/layout.tsx",
      "route": "/",
      "phase": "layout",
      "meta": {
        "moduleType": "layout",
        "segmentGroups": [
          "marketing",
          "default"
        ]
      },
      "id": "layout:104",
      "startTimeMs": 28552.392347,
      "memoryStartMB": 670.38,
      "endTimeMs": 28579.277316,
      "durationMs": 26.88496899999882,
      "memoryEndMB": 671.13
    },
    {
      "kind": "layout",
      "name": "MarketingGroupLayout",
      "path": "src/app/(marketing)/layout.tsx",
      "route": "/",
      "phase": "layout",
      "meta": {
        "moduleType": "layout",
        "segmentGroups": [
          "marketing"
        ]
      },
      "id": "layout:105",
      "startTimeMs": 28636.413005,
      "memoryStartMB": 673.76,
      "endTimeMs": 28640.464822,
      "durationMs": 4.051817000003211,
      "memoryEndMB": 673.76
    },
    {
      "kind": "layout",
      "name": "MarketingDefaultLocaleLayout",
      "path": "src/app/(marketing)/(default)/layout.tsx",
      "route": "/",
      "phase": "layout",
      "meta": {
        "moduleType": "layout",
        "segmentGroups": [
          "marketing",
          "default"
        ]
      },
      "id": "layout:106",
      "startTimeMs": 28637.683762,
      "memoryStartMB": 673.76,
      "endTimeMs": 28656.501249,
      "durationMs": 18.817487000000256,
      "memoryEndMB": 674.51
    },
    {
      "kind": "layout",
      "name": "MarketingGroupLayout",
      "path": "src/app/(marketing)/layout.tsx",
      "route": "/",
      "phase": "layout",
      "meta": {
        "moduleType": "layout",
        "segmentGroups": [
          "marketing"
        ]
      },
      "id": "layout:107",
      "startTimeMs": 28750.013821,
      "memoryStartMB": 672.14,
      "endTimeMs": 28758.689519,
      "durationMs": 8.675697999999102,
      "memoryEndMB": 672.14
    },
    {
      "kind": "layout",
      "name": "MarketingDefaultLocaleLayout",
      "path": "src/app/(marketing)/(default)/layout.tsx",
      "route": "/",
      "phase": "layout",
      "meta": {
        "moduleType": "layout",
        "segmentGroups": [
          "marketing",
          "default"
        ]
      },
      "id": "layout:108",
      "startTimeMs": 28753.819727,
      "memoryStartMB": 672.14,
      "endTimeMs": 28851.343114,
      "durationMs": 97.5233870000011,
      "memoryEndMB": 672.89
    },
    {
      "kind": "layout",
      "name": "MarketingGroupLayout",
      "path": "src/app/(marketing)/layout.tsx",
      "route": "/",
      "phase": "layout",
      "meta": {
        "moduleType": "layout",
        "segmentGroups": [
          "marketing"
        ]
      },
      "id": "layout:109",
      "startTimeMs": 29107.998664,
      "memoryStartMB": 542.68,
      "endTimeMs": 29111.96325,
      "durationMs": 3.964586000001873,
      "memoryEndMB": 542.68
    },
    {
      "kind": "layout",
      "name": "MarketingDefaultLocaleLayout",
      "path": "src/app/(marketing)/(default)/layout.tsx",
      "route": "/",
      "phase": "layout",
      "meta": {
        "moduleType": "layout",
        "segmentGroups": [
          "marketing",
          "default"
        ]
      },
      "id": "layout:110",
      "startTimeMs": 29108.952204,
      "memoryStartMB": 542.68,
      "endTimeMs": 29130.965505,
      "durationMs": 22.013300999999046,
      "memoryEndMB": 543.43
    },
    {
      "kind": "layout",
      "name": "MarketingGroupLayout",
      "path": "src/app/(marketing)/layout.tsx",
      "route": "/",
      "phase": "layout",
      "meta": {
        "moduleType": "layout",
        "segmentGroups": [
          "marketing"
        ]
      },
      "id": "layout:111",
      "startTimeMs": 29179.072546,
      "memoryStartMB": 546.05,
      "endTimeMs": 29234.846294,
      "durationMs": 55.773747999999614,
      "memoryEndMB": 546.05
    },
    {
      "kind": "layout",
      "name": "MarketingDefaultLocaleLayout",
      "path": "src/app/(marketing)/(default)/layout.tsx",
      "route": "/",
      "phase": "layout",
      "meta": {
        "moduleType": "layout",
        "segmentGroups": [
          "marketing",
          "default"
        ]
      },
      "id": "layout:112",
      "startTimeMs": 29180.028146,
      "memoryStartMB": 546.05,
      "endTimeMs": 29283.613299,
      "durationMs": 103.58515299999999,
      "memoryEndMB": 546.8
    },
    {
      "kind": "layout",
      "name": "MarketingGroupLayout",
      "path": "src/app/(marketing)/layout.tsx",
      "route": "/",
      "phase": "layout",
      "meta": {
        "moduleType": "layout",
        "segmentGroups": [
          "marketing"
        ]
      },
      "id": "layout:113",
      "startTimeMs": 30085.552883,
      "memoryStartMB": 553.38,
      "endTimeMs": 30091.451838,
      "durationMs": 5.898955000000569,
      "memoryEndMB": 553.38
    },
    {
      "kind": "layout",
      "name": "MarketingDefaultLocaleLayout",
      "path": "src/app/(marketing)/(default)/layout.tsx",
      "route": "/",
      "phase": "layout",
      "meta": {
        "moduleType": "layout",
        "segmentGroups": [
          "marketing",
          "default"
        ]
      },
      "id": "layout:114",
      "startTimeMs": 30086.576385,
      "memoryStartMB": 553.38,
      "endTimeMs": 30115.892903,
      "durationMs": 29.316517999999633,
      "memoryEndMB": 554.13
    },
    {
      "kind": "layout",
      "name": "MarketingGroupLayout",
      "path": "src/app/(marketing)/layout.tsx",
      "route": "/",
      "phase": "layout",
      "meta": {
        "moduleType": "layout",
        "segmentGroups": [
          "marketing"
        ]
      },
      "id": "layout:115",
      "startTimeMs": 30170.950315,
      "memoryStartMB": 556.76,
      "endTimeMs": 30174.923752,
      "durationMs": 3.9734370000005583,
      "memoryEndMB": 556.76
    },
    {
      "kind": "layout",
      "name": "MarketingDefaultLocaleLayout",
      "path": "src/app/(marketing)/(default)/layout.tsx",
      "route": "/",
      "phase": "layout",
      "meta": {
        "moduleType": "layout",
        "segmentGroups": [
          "marketing",
          "default"
        ]
      },
      "id": "layout:116",
      "startTimeMs": 30171.995572,
      "memoryStartMB": 556.76,
      "endTimeMs": 30191.451905,
      "durationMs": 19.456333000001905,
      "memoryEndMB": 557.51
    },
    {
      "kind": "layout",
      "name": "MarketingGroupLayout",
      "path": "src/app/(marketing)/layout.tsx",
      "route": "/",
      "phase": "layout",
      "meta": {
        "moduleType": "layout",
        "segmentGroups": [
          "marketing"
        ]
      },
      "id": "layout:117",
      "startTimeMs": 30270.245544,
      "memoryStartMB": 555.16,
      "endTimeMs": 30274.066236,
      "durationMs": 3.820691999997507,
      "memoryEndMB": 555.16
    },
    {
      "kind": "layout",
      "name": "MarketingDefaultLocaleLayout",
      "path": "src/app/(marketing)/(default)/layout.tsx",
      "route": "/",
      "phase": "layout",
      "meta": {
        "moduleType": "layout",
        "segmentGroups": [
          "marketing",
          "default"
        ]
      },
      "id": "layout:118",
      "startTimeMs": 30271.459076,
      "memoryStartMB": 555.16,
      "endTimeMs": 30299.891096,
      "durationMs": 28.432020000000193,
      "memoryEndMB": 555.91
    },
    {
      "kind": "layout",
      "name": "MarketingGroupLayout",
      "path": "src/app/(marketing)/layout.tsx",
      "route": "/",
      "phase": "layout",
      "meta": {
        "moduleType": "layout",
        "segmentGroups": [
          "marketing"
        ]
      },
      "id": "layout:119",
      "startTimeMs": 30361.742807,
      "memoryStartMB": 558.54,
      "endTimeMs": 30379.093962,
      "durationMs": 17.35115500000029,
      "memoryEndMB": 558.54
    },
    {
      "kind": "layout",
      "name": "MarketingDefaultLocaleLayout",
      "path": "src/app/(marketing)/(default)/layout.tsx",
      "route": "/",
      "phase": "layout",
      "meta": {
        "moduleType": "layout",
        "segmentGroups": [
          "marketing",
          "default"
        ]
      },
      "id": "layout:120",
      "startTimeMs": 30376.56672,
      "memoryStartMB": 558.54,
      "endTimeMs": 30410.041027,
      "durationMs": 33.47430700000041,
      "memoryEndMB": 559.29
    },
    {
      "kind": "layout",
      "name": "MarketingGroupLayout",
      "path": "src/app/(marketing)/layout.tsx",
      "route": "/",
      "phase": "layout",
      "meta": {
        "moduleType": "layout",
        "segmentGroups": [
          "marketing"
        ]
      },
      "id": "layout:121",
      "startTimeMs": 30531.65878,
      "memoryStartMB": 556.25,
      "endTimeMs": 30541.747654,
      "durationMs": 10.088873999997304,
      "memoryEndMB": 556.25
    },
    {
      "kind": "layout",
      "name": "MarketingDefaultLocaleLayout",
      "path": "src/app/(marketing)/(default)/layout.tsx",
      "route": "/",
      "phase": "layout",
      "meta": {
        "moduleType": "layout",
        "segmentGroups": [
          "marketing",
          "default"
        ]
      },
      "id": "layout:122",
      "startTimeMs": 30532.671887,
      "memoryStartMB": 556.25,
      "endTimeMs": 30560.818559,
      "durationMs": 28.146671999998944,
      "memoryEndMB": 557
    },
    {
      "kind": "layout",
      "name": "MarketingGroupLayout",
      "path": "src/app/(marketing)/layout.tsx",
      "route": "/",
      "phase": "layout",
      "meta": {
        "moduleType": "layout",
        "segmentGroups": [
          "marketing"
        ]
      },
      "id": "layout:123",
      "startTimeMs": 30632.432984,
      "memoryStartMB": 559.63,
      "endTimeMs": 30636.071573,
      "durationMs": 3.638589000001957,
      "memoryEndMB": 559.63
    },
    {
      "kind": "layout",
      "name": "MarketingDefaultLocaleLayout",
      "path": "src/app/(marketing)/(default)/layout.tsx",
      "route": "/",
      "phase": "layout",
      "meta": {
        "moduleType": "layout",
        "segmentGroups": [
          "marketing",
          "default"
        ]
      },
      "id": "layout:124",
      "startTimeMs": 30633.381989,
      "memoryStartMB": 559.63,
      "endTimeMs": 30654.695847,
      "durationMs": 21.31385799999771,
      "memoryEndMB": 560.38
    },
    {
      "kind": "layout",
      "name": "MarketingGroupLayout",
      "path": "src/app/(marketing)/layout.tsx",
      "route": "/",
      "phase": "layout",
      "meta": {
        "moduleType": "layout",
        "segmentGroups": [
          "marketing"
        ]
      },
      "id": "layout:125",
      "startTimeMs": 30745.843425,
      "memoryStartMB": 556.32,
      "endTimeMs": 30749.160745,
      "durationMs": 3.317320000001928,
      "memoryEndMB": 556.32
    },
    {
      "kind": "layout",
      "name": "MarketingDefaultLocaleLayout",
      "path": "src/app/(marketing)/(default)/layout.tsx",
      "route": "/",
      "phase": "layout",
      "meta": {
        "moduleType": "layout",
        "segmentGroups": [
          "marketing",
          "default"
        ]
      },
      "id": "layout:126",
      "startTimeMs": 30746.822453,
      "memoryStartMB": 556.32,
      "endTimeMs": 30770.632472,
      "durationMs": 23.810019000000466,
      "memoryEndMB": 556.94
    },
    {
      "kind": "layout",
      "name": "MarketingGroupLayout",
      "path": "src/app/(marketing)/layout.tsx",
      "route": "/",
      "phase": "layout",
      "meta": {
        "moduleType": "layout",
        "segmentGroups": [
          "marketing"
        ]
      },
      "id": "layout:127",
      "startTimeMs": 30859.955842,
      "memoryStartMB": 564.32,
      "endTimeMs": 30863.470415,
      "durationMs": 3.5145730000003823,
      "memoryEndMB": 564.44
    },
    {
      "kind": "layout",
      "name": "MarketingDefaultLocaleLayout",
      "path": "src/app/(marketing)/(default)/layout.tsx",
      "route": "/",
      "phase": "layout",
      "meta": {
        "moduleType": "layout",
        "segmentGroups": [
          "marketing",
          "default"
        ]
      },
      "id": "layout:128",
      "startTimeMs": 30860.958874,
      "memoryStartMB": 564.32,
      "endTimeMs": 30881.773418,
      "durationMs": 20.81454400000075,
      "memoryEndMB": 565.07
    },
    {
      "kind": "layout",
      "name": "MarketingGroupLayout",
      "path": "src/app/(marketing)/layout.tsx",
      "route": "/",
      "phase": "layout",
      "meta": {
        "moduleType": "layout",
        "segmentGroups": [
          "marketing"
        ]
      },
      "id": "layout:129",
      "startTimeMs": 31616.512625,
      "memoryStartMB": 571.26,
      "endTimeMs": 31619.990474,
      "durationMs": 3.477848999998969,
      "memoryEndMB": 571.26
    },
    {
      "kind": "layout",
      "name": "MarketingDefaultLocaleLayout",
      "path": "src/app/(marketing)/(default)/layout.tsx",
      "route": "/",
      "phase": "layout",
      "meta": {
        "moduleType": "layout",
        "segmentGroups": [
          "marketing",
          "default"
        ]
      },
      "id": "layout:130",
      "startTimeMs": 31617.34059,
      "memoryStartMB": 571.26,
      "endTimeMs": 31640.035612,
      "durationMs": 22.69502199999988,
      "memoryEndMB": 572.01
    },
    {
      "kind": "layout",
      "name": "MarketingGroupLayout",
      "path": "src/app/(marketing)/layout.tsx",
      "route": "/",
      "phase": "layout",
      "meta": {
        "moduleType": "layout",
        "segmentGroups": [
          "marketing"
        ]
      },
      "id": "layout:131",
      "startTimeMs": 31689.587057,
      "memoryStartMB": 574.64,
      "endTimeMs": 31693.54608,
      "durationMs": 3.9590229999994335,
      "memoryEndMB": 574.64
    },
    {
      "kind": "layout",
      "name": "MarketingDefaultLocaleLayout",
      "path": "src/app/(marketing)/(default)/layout.tsx",
      "route": "/",
      "phase": "layout",
      "meta": {
        "moduleType": "layout",
        "segmentGroups": [
          "marketing",
          "default"
        ]
      },
      "id": "layout:132",
      "startTimeMs": 31690.641071,
      "memoryStartMB": 574.64,
      "endTimeMs": 31718.420474,
      "durationMs": 27.779403000000457,
      "memoryEndMB": 575.26
    },
    {
      "kind": "layout",
      "name": "MarketingGroupLayout",
      "path": "src/app/(marketing)/layout.tsx",
      "route": "/",
      "phase": "layout",
      "meta": {
        "moduleType": "layout",
        "segmentGroups": [
          "marketing"
        ]
      },
      "id": "layout:133",
      "startTimeMs": 31780.543746,
      "memoryStartMB": 577.89,
      "endTimeMs": 31783.774171,
      "durationMs": 3.23042500000156,
      "memoryEndMB": 577.89
    },
    {
      "kind": "layout",
      "name": "MarketingDefaultLocaleLayout",
      "path": "src/app/(marketing)/(default)/layout.tsx",
      "route": "/",
      "phase": "layout",
      "meta": {
        "moduleType": "layout",
        "segmentGroups": [
          "marketing",
          "default"
        ]
      },
      "id": "layout:134",
      "startTimeMs": 31781.457578,
      "memoryStartMB": 577.89,
      "endTimeMs": 31815.323796,
      "durationMs": 33.86621799999921,
      "memoryEndMB": 572.99
    },
    {
      "kind": "layout",
      "name": "MarketingGroupLayout",
      "path": "src/app/(marketing)/layout.tsx",
      "route": "/",
      "phase": "layout",
      "meta": {
        "moduleType": "layout",
        "segmentGroups": [
          "marketing"
        ]
      },
      "id": "layout:135",
      "startTimeMs": 31869.680292,
      "memoryStartMB": 575.61,
      "endTimeMs": 31872.673111,
      "durationMs": 2.9928189999991446,
      "memoryEndMB": 575.61
    },
    {
      "kind": "layout",
      "name": "MarketingDefaultLocaleLayout",
      "path": "src/app/(marketing)/(default)/layout.tsx",
      "route": "/",
      "phase": "layout",
      "meta": {
        "moduleType": "layout",
        "segmentGroups": [
          "marketing",
          "default"
        ]
      },
      "id": "layout:136",
      "startTimeMs": 31870.610797,
      "memoryStartMB": 575.61,
      "endTimeMs": 31898.170832,
      "durationMs": 27.560034999998607,
      "memoryEndMB": 576.24
    },
    {
      "kind": "layout",
      "name": "MarketingGroupLayout",
      "path": "src/app/(marketing)/layout.tsx",
      "route": "/",
      "phase": "layout",
      "meta": {
        "moduleType": "layout",
        "segmentGroups": [
          "marketing"
        ]
      },
      "id": "layout:137",
      "startTimeMs": 31958.530744,
      "memoryStartMB": 578.86,
      "endTimeMs": 31961.344238,
      "durationMs": 2.8134940000018105,
      "memoryEndMB": 578.86
    },
    {
      "kind": "layout",
      "name": "MarketingDefaultLocaleLayout",
      "path": "src/app/(marketing)/(default)/layout.tsx",
      "route": "/",
      "phase": "layout",
      "meta": {
        "moduleType": "layout",
        "segmentGroups": [
          "marketing",
          "default"
        ]
      },
      "id": "layout:138",
      "startTimeMs": 31959.472865,
      "memoryStartMB": 578.86,
      "endTimeMs": 31978.792406,
      "durationMs": 19.319541000000754,
      "memoryEndMB": 579.61
    },
    {
      "kind": "layout",
      "name": "MarketingGroupLayout",
      "path": "src/app/(marketing)/layout.tsx",
      "route": "/",
      "phase": "layout",
      "meta": {
        "moduleType": "layout",
        "segmentGroups": [
          "marketing"
        ]
      },
      "id": "layout:139",
      "startTimeMs": 32062.592368,
      "memoryStartMB": 576.09,
      "endTimeMs": 32069.848232,
      "durationMs": 7.255863999998837,
      "memoryEndMB": 576.09
    },
    {
      "kind": "layout",
      "name": "MarketingDefaultLocaleLayout",
      "path": "src/app/(marketing)/(default)/layout.tsx",
      "route": "/",
      "phase": "layout",
      "meta": {
        "moduleType": "layout",
        "segmentGroups": [
          "marketing",
          "default"
        ]
      },
      "id": "layout:140",
      "startTimeMs": 32066.310945,
      "memoryStartMB": 576.09,
      "endTimeMs": 32091.232799,
      "durationMs": 24.921854000000167,
      "memoryEndMB": 576.72
    },
    {
      "kind": "layout",
      "name": "MarketingGroupLayout",
      "path": "src/app/(marketing)/layout.tsx",
      "route": "/",
      "phase": "layout",
      "meta": {
        "moduleType": "layout",
        "segmentGroups": [
          "marketing"
        ]
      },
      "id": "layout:141",
      "startTimeMs": 32173.870152,
      "memoryStartMB": 583.47,
      "endTimeMs": 32176.156885,
      "durationMs": 2.2867330000008224,
      "memoryEndMB": 583.47
    },
    {
      "kind": "layout",
      "name": "MarketingDefaultLocaleLayout",
      "path": "src/app/(marketing)/(default)/layout.tsx",
      "route": "/",
      "phase": "layout",
      "meta": {
        "moduleType": "layout",
        "segmentGroups": [
          "marketing",
          "default"
        ]
      },
      "id": "layout:142",
      "startTimeMs": 32174.689737,
      "memoryStartMB": 583.47,
      "endTimeMs": 32192.17362,
      "durationMs": 17.483883000000787,
      "memoryEndMB": 584.09
    },
    {
      "kind": "layout",
      "name": "MarketingGroupLayout",
      "path": "src/app/(marketing)/layout.tsx",
      "route": "/",
      "phase": "layout",
      "meta": {
        "moduleType": "layout",
        "segmentGroups": [
          "marketing"
        ]
      },
      "id": "layout:143",
      "startTimeMs": 32257.957424,
      "memoryStartMB": 581.07,
      "endTimeMs": 32261.369918,
      "durationMs": 3.4124940000001516,
      "memoryEndMB": 581.07
    },
    {
      "kind": "layout",
      "name": "MarketingDefaultLocaleLayout",
      "path": "src/app/(marketing)/(default)/layout.tsx",
      "route": "/",
      "phase": "layout",
      "meta": {
        "moduleType": "layout",
        "segmentGroups": [
          "marketing",
          "default"
        ]
      },
      "id": "layout:144",
      "startTimeMs": 32258.955314,
      "memoryStartMB": 581.07,
      "endTimeMs": 32275.150451,
      "durationMs": 16.195137000002433,
      "memoryEndMB": 581.82
    },
    {
      "kind": "layout",
      "name": "MarketingGroupLayout",
      "path": "src/app/(marketing)/layout.tsx",
      "route": "/",
      "phase": "layout",
      "meta": {
        "moduleType": "layout",
        "segmentGroups": [
          "marketing"
        ]
      },
      "id": "layout:145",
      "startTimeMs": 32944.262388,
      "memoryStartMB": 598.51,
      "endTimeMs": 32948.151952,
      "durationMs": 3.8895639999973355,
      "memoryEndMB": 598.51
    },
    {
      "kind": "layout",
      "name": "MarketingDefaultLocaleLayout",
      "path": "src/app/(marketing)/(default)/layout.tsx",
      "route": "/",
      "phase": "layout",
      "meta": {
        "moduleType": "layout",
        "segmentGroups": [
          "marketing",
          "default"
        ]
      },
      "id": "layout:146",
      "startTimeMs": 32945.234603,
      "memoryStartMB": 598.51,
      "endTimeMs": 32965.677468,
      "durationMs": 20.44286500000453,
      "memoryEndMB": 599.26
    }
  ]
}